pyqt_current_exception_message_box.py
pyqt_current_exception_message_box-0.1.0a0.dist-info/licenses/LICENSE
pyqt_current_exception_message_box-0.1.0a0.dist-info/METADATA
pyqt_current_exception_message_box-0.1.0a0.dist-info/WHEEL
pyqt_current_exception_message_box-0.1.0a0.dist-info/top_level.txt
pyqt_current_exception_message_box-0.1.0a0.dist-info/RECORD
