Metadata-Version: 2.4
Name: pyqt-current-exception-message-box
Version: 0.1.0a0
Summary: A simple utility to display the current exception in a PyQt message box.
Author-email: Jifeng Wu <jifengwu2k@gmail.com>
License-Expression: MIT
Project-URL: Homepage, https://github.com/jifengwu2k/pyqt-current-exception-message-box
Project-URL: Bug Tracker, https://github.com/jifengwu2k/pyqt-current-exception-message-box/issues
Classifier: Programming Language :: Python :: 2
Classifier: Programming Language :: Python :: 3
Classifier: Operating System :: OS Independent
Requires-Python: >=2
License-File: LICENSE
Requires-Dist: detect-qt-binding
Dynamic: license-file
